LICENSE
MANIFEST.in
README.rst
setup.py
test.py
packagedb_cli.egg-info/PKG-INFO
packagedb_cli.egg-info/SOURCES.txt
packagedb_cli.egg-info/dependency_links.txt
packagedb_cli.egg-info/entry_points.txt
packagedb_cli.egg-info/requires.txt
packagedb_cli.egg-info/top_level.txt
pkgdb2client/__init__.py
pkgdb2client/admin.py
pkgdb2client/cli.py
pkgdb2client/utils.py