Metadata-Version: 1.1
Name: packagedb-cli
Version: 2.13
Summary: A command line tool to access the Fedora Package Database.
Home-page: https://fedorahosted.org/packagedb-cli/
Author: Pierre-Yves Chibon
Author-email: pingou@pingoured.fr
License: GPLv2+
Download-URL: https://fedorahosted.org/releases/p/a/packagedb-cli/
Platform: UNKNOWN
Classifier: Development Status :: 5 - Production/Stable
Classifier: Environment :: Console
Classifier: Intended Audience :: Developers
Classifier: License :: OSI Approved :: GNU General Public License v2 or later (GPLv2+)
Classifier: Operating System :: OS Independent
Classifier: Programming Language :: Python :: 2.6
Classifier: Programming Language :: Python :: 2.7
Classifier: Topic :: Software Development :: Libraries
